odoo/addons/mrp_sale_info/README.rst
odoo/addons/mrp_sale_info/__init__.py
odoo/addons/mrp_sale_info/__manifest__.py
odoo/addons/mrp_sale_info/i18n/de.po
odoo/addons/mrp_sale_info/i18n/es.po
odoo/addons/mrp_sale_info/i18n/fr.po
odoo/addons/mrp_sale_info/i18n/it.po
odoo/addons/mrp_sale_info/i18n/mrp_sale_info.pot
odoo/addons/mrp_sale_info/i18n/pt_BR.po
odoo/addons/mrp_sale_info/i18n/zh_CN.po
odoo/addons/mrp_sale_info/models/__init__.py
odoo/addons/mrp_sale_info/models/mrp_production.py
odoo/addons/mrp_sale_info/models/mrp_workorder.py
odoo/addons/mrp_sale_info/models/sale_order.py
odoo/addons/mrp_sale_info/models/sale_order_line.py
odoo/addons/mrp_sale_info/models/stock_rule.py
odoo/addons/mrp_sale_info/readme/CONTRIBUTORS.rst
odoo/addons/mrp_sale_info/readme/DESCRIPTION.rst
odoo/addons/mrp_sale_info/readme/USAGE.rst
odoo/addons/mrp_sale_info/static/description/icon.png
odoo/addons/mrp_sale_info/static/description/index.html
odoo/addons/mrp_sale_info/tests/__init__.py
odoo/addons/mrp_sale_info/tests/test_mrp_sale_info.py
odoo/addons/mrp_sale_info/views/mrp_production.xml
odoo/addons/mrp_sale_info/views/mrp_workorder.xml
odoo14_addon_mrp_sale_info-14.0.2.2.1.dist-info/METADATA
odoo14_addon_mrp_sale_info-14.0.2.2.1.dist-info/WHEEL
odoo14_addon_mrp_sale_info-14.0.2.2.1.dist-info/top_level.txt
odoo14_addon_mrp_sale_info-14.0.2.2.1.dist-info/RECORD
